Metadata-Version: 2.1
Name: srufinder
Version: 0.2.1
Summary: SRUFinder: Find and subtype SRUs, mini-arrays, and CRISPR arrays by repeat matching
Home-page: https://github.com/Russel88/SRUFinder
Author: Jakob Russel
Author-email: russel2620@gmail.com
License: UNKNOWN
Download-URL: https://github.com/Russel88/SRUFinder/archive/v0.2.1.tar.gz
Platform: UNKNOWN
Classifier: Programming Language :: Python :: 3
Classifier: License :: OSI Approved :: MIT License
Classifier: Operating System :: OS Independent
Classifier: Topic :: Scientific/Engineering :: Bio-Informatics
Classifier: Topic :: Software Development :: Libraries :: Python Modules
Classifier: Development Status :: 4 - Beta
Requires-Python: >=3.8
License-File: LICENSE
